lesspass_client/__init__.py
lesspass_client/__main__.py
lesspass_client/api.py
lesspass_client/boolean.py
lesspass_client/cli.py
lesspass_client-0.2.0.dist-info/entry_points.txt
lesspass_client-0.2.0.dist-info/WHEEL
lesspass_client-0.2.0.dist-info/METADATA
lesspass_client-0.2.0.dist-info/RECORD
