Metadata-Version: 2.1
Name: lesspass-client
Version: 0.2.0
Summary: A LessPass API client written in Python.
Home-page: https://github.com/SuperSonicHub1/lesspass-client
License: Unlicense
Keywords: lesspass,cli,password,manager
Author: Kyle Williams
Author-email: kyle.anthony.williams2@gmail.com
Requires-Python: >=3.8,<4.0
Classifier: License :: Other/Proprietary License
Classifier: License :: Public Domain
Classifier: Programming Language :: Python :: 3
Classifier: Programming Language :: Python :: 3.10
Classifier: Programming Language :: Python :: 3.8
Classifier: Programming Language :: Python :: 3.9
Classifier: Topic :: Internet
Classifier: Topic :: Security
Requires-Dist: lesspass (>=10.0.2,<11.0.0)
Requires-Dist: requests (>=2.26.0,<3.0.0)
Project-URL: Documentation, https://github.com/SuperSonicHub1/lesspass-client#readme
Project-URL: Repository, https://github.com/SuperSonicHub1/lesspass-client
